story_time/Info.txt
story_time/XML_write.py
story_time/__init__.py
story_time/main.py
story_time/user_interface.py
story_time/util.py
story_time/Icons/Entwurf.jpg
story_time/Icons/calendar_icon.png
story_time/Icons/default_img.png
story_time/Icons/default_img_txt.png
story_time/Icons/folder_icon.png
story_time/Icons/folder_icon_w.png
story_time/Icons/help_icon.png
story_time/Icons/import_icon.png
story_time/Icons/photo_icon.png
story_time/Icons/photo_icon_w.png
story_time/Icons/save_icon.png
story_time/Icons/save_icon_w.png
story_time/Icons/story_time_icons.drawio
story_time/Icons/webcam_icon.png
story_time/Icons/webcam_icon_w.png
story_time-0.5.0.dist-info/LICENSE
story_time-0.5.0.dist-info/METADATA
story_time-0.5.0.dist-info/WHEEL
story_time-0.5.0.dist-info/entry_points.txt
story_time-0.5.0.dist-info/top_level.txt
story_time-0.5.0.dist-info/RECORD
