Metadata-Version: 2.1
Name: story-time
Version: 0.5.0
Summary: Digital Diary written in wxPython
Home-page: https://github.com/chbauman/StoryTime
Author: Christian Baumann
Author-email: chris.python.notifyer@gmail.com
License: MIT
Platform: UNKNOWN
Classifier: Programming Language :: Python
Classifier: Programming Language :: Python :: 3.6
Classifier: Operating System :: OS Independent
Classifier: Topic :: Utilities
Requires-Python: >=3.6
Requires-Dist: wxPython
Requires-Dist: opencv-python
Requires-Dist: numpy
Requires-Dist: Pillow
Requires-Dist: six
